README.txt
setup.py
sape/__init__.py
sape/client.py
sape/phpserialize.py
sape/provider.py
sape/version.py
sape.egg-info/PKG-INFO
sape.egg-info/SOURCES.txt
sape.egg-info/dependency_links.txt
sape.egg-info/top_level.txt
sape/django/__init__.py
sape/django/context_processors.py
sape/django/management/__init__.py
sape/django/management/commands/__init__.py
sape/django/management/commands/sape_refresh.py